{
  "fabric:load_conditions": [
    {
      "condition": "mcda:item_enabled",
      "values": [
        "mcda:teleportation_robe_leggings"
      ]
    }
  ],
  "type": "minecraft:crafting_shaped",
  "pattern": [
    "WWW",
    "WSW",
    "B B"
  ],
  "key": {
    "W": {
      "item": "mcda:fabric_bolt_purple"
    },
    "S": {
      "item": "minecraft:ender_eye"
    },
    "B": {
      "item": "mcda:fabric_bolt_yellow"
    }
  },
  "result": {
    "item": "mcda:teleportation_robe_leggings",
    "count": 1
  }
}